jacdac/__init__.py
jacdac/bus.py
jacdac/constants.py
jacdac/pack.py
jacdac/packet.py
jacdac/settings_file.py
jacdac/transport.py
jacdac/util.py
jacdac/accelerometer/__init__.py
jacdac/accelerometer/client.py
jacdac/accelerometer/constants.py
jacdac/acidity/__init__.py
jacdac/acidity/client.py
jacdac/acidity/constants.py
jacdac/air_pressure/__init__.py
jacdac/air_pressure/client.py
jacdac/air_pressure/constants.py
jacdac/air_quality_index/__init__.py
jacdac/air_quality_index/client.py
jacdac/air_quality_index/constants.py
jacdac/arcade_gamepad/__init__.py
jacdac/arcade_gamepad/client.py
jacdac/arcade_gamepad/constants.py
jacdac/arcade_sound/__init__.py
jacdac/arcade_sound/client.py
jacdac/arcade_sound/constants.py
jacdac/azure_iot_hub_health/__init__.py
jacdac/azure_iot_hub_health/client.py
jacdac/azure_iot_hub_health/constants.py
jacdac/azure_iot_hub_health/server.py
jacdac/azure_iot_hub_health/test.py
jacdac/barcode_reader/__init__.py
jacdac/barcode_reader/client.py
jacdac/barcode_reader/constants.py
jacdac/bit_radio/__init__.py
jacdac/bit_radio/client.py
jacdac/bit_radio/constants.py
jacdac/bootloader/__init__.py
jacdac/bootloader/constants.py
jacdac/braille_display/__init__.py
jacdac/braille_display/client.py
jacdac/braille_display/constants.py
jacdac/bridge/__init__.py
jacdac/bridge/constants.py
jacdac/button/__init__.py
jacdac/button/client.py
jacdac/button/client_base.py
jacdac/button/constants.py
jacdac/button/server.py
jacdac/button/test.py
jacdac/buzzer/__init__.py
jacdac/buzzer/client.py
jacdac/buzzer/constants.py
jacdac/capacitive_button/__init__.py
jacdac/capacitive_button/client.py
jacdac/capacitive_button/constants.py
jacdac/character_screen/__init__.py
jacdac/character_screen/client.py
jacdac/character_screen/constants.py
jacdac/codal_message_bus/__init__.py
jacdac/codal_message_bus/client.py
jacdac/codal_message_bus/constants.py
jacdac/color/__init__.py
jacdac/color/client.py
jacdac/color/constants.py
jacdac/compass/__init__.py
jacdac_python-0.2.15.dist-info/LICENSE
jacdac_python-0.2.15.dist-info/METADATA
jacdac_python-0.2.15.dist-info/WHEEL
jacdac_python-0.2.15.dist-info/top_level.txt
jacdac_python-0.2.15.dist-info/RECORD
