Metadata-Version: 2.1
Name: jacdac-python
Version: 0.2.15
Summary: Python client package for Jacdac
Home-page: https://microsoft.github.io/jacdac-docs/clients/python/
Author: Microsoft Corporation
License: MIT
Project-URL: Bug Tracker, https://github.com/microsoft/jacdac/issues
Project-URL: Discussions, https://github.com/microsoft/jacdac/discussions
Platform: UNKNOWN
Classifier: Intended Audience :: Developers
Classifier: Intended Audience :: Education
Classifier: Intended Audience :: Science/Research
Classifier: License :: OSI Approved :: MIT License
Classifier: Operating System :: Unix
Classifier: Operating System :: POSIX
Classifier: Operating System :: Microsoft :: Windows
Classifier: Programming Language :: Python
Classifier: Programming Language :: Python :: 3
Classifier: Programming Language :: Python :: 3.7
Classifier: Programming Language :: Python :: 3.8
Classifier: Programming Language :: Python :: 3.9
Classifier: Programming Language :: Python :: Implementation :: CPython
Classifier: Programming Language :: Python :: Implementation :: PyPy
Classifier: Topic :: System :: Hardware
Classifier: Topic :: Software Development :: Embedded Systems
License-File: LICENSE
Requires-Dist: websocket-client
Requires-Dist: websockets
Requires-Dist: requests
Provides-Extra: pi
Requires-Dist: spidev ; extra == 'pi'
Provides-Extra: serial
Requires-Dist: pyserial ; extra == 'serial'
Provides-Extra: spi
Requires-Dist: spidev ; extra == 'spi'
